Workbook
Name Slicer_Quarter: #N/A
Name Slicer_Month: #N/A
Name Slicer_Segment: #N/A
Name Slicer_Year: #N/A

Sheet data
A1: Segment | B1: Country | C1: Product_Name | D1: Customer_ID | E1: Product_ID | F1: Customer_Name | G1: Discount Band | H1: Date | I1: Month | J1: Quarter | K1: Year | L1: Units Sold | M1: Manufacturing Price | N1: Sale Price | O1: Gross Sales | P1: Discounts | Q1: Net Sales | R1: Sales ('000) | S1: COGS | T1: Profit
A2: Enterprise | B2: USA | C2: X-Terrain | D2: CUST_ID_001 | E2: PROD_ID_001 | F2: James Smith | G2: None | H2: 44096 | I2: Sep | J2: Q3 | K2: 2020 | L2: 414 | M2: 6.00 | N2: 188.00 | O2: 77.832 | P2: - | Q2: 77.832 | R2: 43.13 | S2: 2.484 | T2: 75.348
A3: Midmarket | B3: Canada | C3: City Cruiser | D3: CUST_ID_002 | E3: PROD_ID_002 | F3: Emma Johnson | G3: None | H3: 43841 | I3: Jan | J3: Q1 | K3: 2020 | L3: 659 | M3: 12.00 | N3: 23.00 | O3: 15.157 | P3: - | Q3: 15.157 | R3: 45505 | S3: 7.908 | T3: 7.249
A4: Small Business | B4: England | C4: City Cruiser | D4: CUST_ID_003 | E4: PROD_ID_002 | F4: Noah Williams | G4: None | H4: 44223 | I4: Jan | J4: Q1 | K4: 2021 | L4: 946 | M4: 12.00 | N4: 450.00 | O4: 425.7 | P4: - | Q4: 425.7 | R4: 236.40 | S4: 11.352 | T4: 414.348
A5: Government | B5: France | C5: City Cruiser | D5: CUST_ID_004 | E5: PROD_ID_002 | F5: Olivia Brown | G5: None | H5: 44044 | I5: Aug | J5: Q3 | K5: 2020 | L5: 2.07 | M5: 12.00 | N5: 525.00 | O5: 1,086,750 | P5: - | Q5: 1,086,750 | R5: 603.75 | S5: 24.84 | T5: 1,061,910
A6: Channel Partners | B6: Germany | C6: City Cruiser | D6: CUST_ID_005 | E6: PROD_ID_002 | F6: Liam Jones | G6: None | H6: 44385 | I6: Jul | J6: Q3 | K6: 2021 | L6: 1.094 | M6: 12.00 | N6: 18.00 | O6: 19.692 | P6: - | Q6: 19.692 | R6: 34608 | S6: 13.128 | T6: 6.564
A7: Midmarket | B7: Italy | C7: City Cruiser | D7: CUST_ID_006 | E7: PROD_ID_002 | F7: Ava Davis | G7: None | H7: 44467 | I7: Sep | J7: Q3 | K7: 2021 | L7: 2.582 | M7: 12.00 | N7: 23.00 | O7: 59.386 | P7: - | Q7: 59.386 | R7: 32.28 | S7: 30.984 | T7: 28.402
A8: Enterprise | B8: India | C8: Speedster | D8: CUST_ID_007 | E8: PROD_ID_003 | F8: Ethan Miller | G8: None | H8: 44100 | I8: Sep | J8: Q3 | K8: 2020 | L8: 414 | M8: 148.00 | N8: 188.00 | O8: 77.832 | P8: - | Q8: 77.832 | R8: 43.13 | S8: 61.272 | T8: 16.56
A9: Government | B9: Japan | C9: Trail Master | D9: CUST_ID_008 | E9: PROD_ID_004 | F9: Isabella Wilson | G9: None | H9: 43872 | I9: Feb | J9: Q1 | K9: 2020 | L9: 1.832 | M9: 308.00 | N9: 525.00 | O9: 961.8 | P9: - | Q9: 961.8 | R9: 534.45 | S9: 564.256 | T9: 397.544
A10: Enterprise | B10: USA | C10: Road Racer | D10: CUST_ID_009 | E10: PROD_ID_005 | F10: Mason Taylor | G10: Low | H10: 44208 | I10: Jan | J10: Q1 | K10: 2021 | L10: 396 | M10: 4.00 | N10: 188.00 | O10: 74.448 | P10: 744 | Q10: 73.704 | R10: 40.84 | S10: 1.584 | T10: 72.12
A11: Channel Partners | B11: Canada | C11: Road Racer | D11: CUST_ID_010 | E11: PROD_ID_005 | F11: Sophia Anderson | G11: Low | H11: 44292 | I11: Apr | J11: Q2 | K11: 2021 | L11: 919 | M11: 4.00 | N11: 18.00 | O11: 16.542 | P11: 165 | Q11: 16.377 | R11: 45939 | S11: 3.676 | T11: 12.701
A12: Small Business | B12: England | C12: Road Racer | D12: CUST_ID_011 | E12: PROD_ID_005 | F12: Benjamin Martinez | G12: Low | H12: 44154 | I12: Nov | J12: Q4 | K12: 2020 | L12: 593 | M12: 4.00 | N12: 450.00 | O12: 266.85 | P12: 2.669 | Q12: 264.182 | R12: 146.72 | S12: 2.372 | T12: 261.81
A13: Small Business | B13: France | C13: X-Terrain | D13: CUST_ID_012 | E13: PROD_ID_001 | F13: Mia Thomas | G13: Low | H13: 44185 | I13: Dec | J13: Q4 | K13: 2020 | L13: 2.998 | M13: 6.00 | N13: 450.00 | O13: 1,349,100 | P13: 13.491 | Q13: 1,335,609 | R13: 741.91 | S13: 17.988 | T13: 1,317,621
A14: Enterprise | B14: Germany | C14: X-Terrain | D14: CUST_ID_013 | E14: PROD_ID_001 | F14: Logan Jackson | G14: Low | H14: 43888 | I14: Feb | J14: Q1 | K14: 2020 | L14: 796 | M14: 6.00 | N14: 188.00 | O14: 149.648 | P14: 1.496 | Q14: 148.152 | R14: 82.05 | S14: 4.776 | T14: 143.376
A15: Channel Partners | B15: Italy | C15: City Cruiser | D15: CUST_ID_014 | E15: PROD_ID_002 | F15: Charlotte White | G15: Low | H15: 44387 | I15: Jul | J15: Q3 | K15: 2021 | L15: 919 | M15: 12.00 | N15: 18.00 | O15: 16.542 | P15: 165 | Q15: 16.377 | R15: 45939 | S15: 11.028 | T15: 5.349
A16: Enterprise | B16: India | C16: Speedster | D16: CUST_ID_015 | E16: PROD_ID_003 | F16: Samuel Taylor | G16: Low | H16: 44284 | I16: Mar | J16: Q1 | K16: 2021 | L16: 796 | M16: 148.00 | N16: 188.00 | O16: 149.648 | P16: 1.496 | Q16: 148.152 | R16: 82.05 | S16: 117.808 | T16: 30.344
A17: Government | B17: Japan | C17: Speedster | D17: CUST_ID_016 | E17: PROD_ID_003 | F17: Harper Davis | G17: Low | H17: 44488 | I17: Oct | J17: Q4 | K17: 2021 | L17: 2.51 | M17: 148.00 | N17: 11.00 | O17: 27.61 | P17: 276 | Q17: 27.334 | R17: 14.50 | S17: 371.48 | T17: -344.146
A18: Small Business | B18: USA | C18: Trail Master | D18: CUST_ID_017 | E18: PROD_ID_004 | F18: Henry Anderson | G18: Low | H18: 44408 | I18: Jul | J18: Q3 | K18: 2021 | L18: 593 | M18: 308.00 | N18: 450.00 | O18: 266.85 | P18: 2.669 | Q18: 264.182 | R18: 146.72 | S18: 182.644 | T18: 81.538
A19: Channel Partners | B19: Canada | C19: Yellow Edition | D19: CUST_ID_018 | E19: PROD_ID_006 | F19: Amelia Garcia | G19: Low | H19: 44284 | I19: Mar | J19: Q1 | K19: 2021 | L19: 2.387 | M19: 320.00 | N19: 18.00 | O19: 42.966 | P19: 430 | Q19: 42.536 | R19: 23.63 | S19: 763.84 | T19: -721.304
A20: Midmarket | B20: England | C20: Yellow Edition | D20: CUST_ID_019 | E20: PROD_ID_006 | F20: Jackson Martinez | G20: Low | H20: 44404 | I20: Jul | J20: Q3 | K20: 2021 | L20: 385 | M20: 320.00 | N20: 23.00 | O20: 8.855 | P20: 89 | Q20: 8.766 | R20: 28216 | S20: 123.2 | T20: -114.434
A21: Small Business | B21: France | C21: Road Racer | D21: CUST_ID_020 | E21: PROD_ID_005 | F21: Abigail Robinson | G21: Low | H21: 44073 | I21: Aug | J21: Q3 | K21: 2020 | L21: 257 | M21: 4.00 | N21: 450.00 | O21: 115.65 | P21: 2.313 | Q21: 113.337 | R21: 62.92 | S21: 1.028 | T21: 112.309
A22: Government | B22: Germany | C22: Road Racer | D22: CUST_ID_021 | E22: PROD_ID_005 | F22: Aiden Lewis | G22: Low | H22: 44119 | I22: Oct | J22: Q4 | K22: 2020 | L22: 2.574 | M22: 4.00 | N22: 11.00 | O22: 28.314 | P22: 566 | Q22: 27.748 | R22: 14.71 | S22: 10.296 | T22: 17.452
A23: Enterprise | B23: Italy | C23: X-Terrain | D23: CUST_ID_022 | E23: PROD_ID_001 | F23: Emily Clark | G23: Low | H23: 44499 | I23: Oct | J23: Q4 | K23: 2021 | L23: 1.992 | M23: 6.00 | N23: 188.00 | O23: 374.496 | P23: 7.49 | Q23: 367.006 | R23: 203.35 | S23: 11.952 | T23: 355.054
A24: Enterprise | B24: India | C24: City Cruiser | D24: CUST_ID_023 | E24: PROD_ID_002 | F24: Sebastian Lee | G24: Low | H24: 44175 | I24: Dec | J24: Q4 | K24: 2020 | L24: 971 | M24: 12.00 | N24: 188.00 | O24: 182.548 | P24: 3.651 | Q24: 178.897 | R24: 99.10 | S24: 11.652 | T24: 167.245
A25: Enterprise | B25: Japan | C25: City Cruiser | D25: CUST_ID_024 | E25: PROD_ID_002 | F25: Elizabeth Green | G25: Low | H25: 43974 | I25: May | J25: Q2 | K25: 2020 | L25: 2.574 | M25: 12.00 | N25: 188.00 | O25: 483.912 | P25: 9.678 | Q25: 474.234 | R25: 262.76 | S25: 30.888 | T25: 443.346
A26: Channel Partners | B26: USA | C26: City Cruiser | D26: CUST_ID_025 | E26: PROD_ID_002 | F26: Alexander Perez | G26: Low | H26: 43879 | I26: Feb | J26: Q1 | K26: 2020 | L26: 2.142 | M26: 12.00 | N26: 18.00 | O26: 38.556 | P26: 771 | Q26: 37.785 | R26: 20.99 | S26: 25.704 | T26: 12.081
A27: Midmarket | B27: Canada | C27: City Cruiser | D27: CUST_ID_026 | E27: PROD_ID_002 | F27: Avery Turner | G27: Low | H27: 43858 | I27: Jan | J27: Q1 | K27: 2020 | L27: 2.31 | M27: 12.00 | N27: 23.00 | O27: 53.13 | P27: 1.063 | Q27: 52.067 | R27: 28.30 | S27: 27.72 | T27: 24.347
A28: Government | B28: England | C28: City Cruiser | D28: CUST_ID_027 | E28: PROD_ID_002 | F28: Michael Hill | G28: Low | H28: 44551 | I28: Dec | J28: Q4 | K28: 2021 | L28: 2.416 | M28: 12.00 | N28: 11.00 | O28: 26.576 | P28: 532 | Q28: 26.044 | R28: 13.81 | S28: 28.992 | T28: -2.948
A29: Government | B29: France | C29: Speedster | D29: CUST_ID_028 | E29: PROD_ID_003 | F29: Sofia Phillips | G29: Low | H29: 44209 | I29: Jan | J29: Q1 | K29: 2021 | L29: 3.559 | M29: 148.00 | N29: 525.00 | O29: 1,868,475 | P29: 37.37 | Q29: 1,831,106 | R29: 1,017.34 | S29: 526.732 | T29: 1,304,374
A30: Enterprise | B30: Germany | C30: Speedster | D30: CUST_ID_029 | E30: PROD_ID_003 | F30: Elijah Martin | G30: Low | H30: 44508 | I30: Nov | J30: Q4 | K30: 2021 | L30: 971 | M30: 148.00 | N30: 188.00 | O30: 182.548 | P30: 3.651 | Q30: 178.897 | R30: 99.10 | S30: 143.708 | T30: 35.189
A31: Enterprise | B31: Italy | C31: Speedster | D31: CUST_ID_030 | E31: PROD_ID_003 | F31: Sophia Turner | G31: Low | H31: 43849 | I31: Jan | J31: Q1 | K31: 2020 | L31: 2.574 | M31: 148.00 | N31: 188.00 | O31: 483.912 | P31: 9.678 | Q31: 474.234 | R31: 262.76 | S31: 380.952 | T31: 93.282
A32: Government | B32: India | C32: Speedster | D32: CUST_ID_031 | E32: PROD_ID_003 | F32: Benjamin Lee | G32: Low | H32: 44042 | I32: Jul | J32: Q3 | K32: 2020 | L32: 653 | M32: 148.00 | N32: 30.00 | O32: 19.59 | P32: 392 | Q32: 19.198 | R32: 24381 | S32: 96.644 | T32: -77.446
A33: Small Business | B33: Japan | C33: Trail Master | D33: CUST_ID_032 | E33: PROD_ID_004 | F33: Mia White | G33: Low | H33: 43882 | I33: Feb | J33: Q1 | K33: 2020 | L33: 257 | M33: 308.00 | N33: 450.00 | O33: 115.65 | P33: 2.313 | Q33: 113.337 | R33: 62.92 | S33: 79.156 | T33: 34.181
A34: Government | B34: USA | C34: Trail Master | D34: CUST_ID_033 | E34: PROD_ID_004 | F34: Logan Garcia | G34: Low | H34: 44224 | I34: Jan | J34: Q1 | K34: 2021 | L34: 319 | M34: 308.00 | N34: 525.00 | O34: 167.475 | P34: 3.35 | Q34: 164.126 | R34: 91.24 | S34: 98.252 | T34: 65.874
A35: Government | B35: Canada | C35: Trail Master | D35: CUST_ID_034 | E35: PROD_ID_004 | F35: Charlotte Davis | G35: Low | H35: 44208 | I35: Jan | J35: Q1 | K35: 2021 | L35: 2.328 | M35: 308.00 | N35: 525.00 | O35: 1,222,200 | P35: 24.444 | Q35: 1,197,756 | R35: 665.42 | S35: 717.024 | T35: 480.732
A36: Government | B36: England | C36: Yellow Edition | D36: CUST_ID_035 | E36: PROD_ID_006 | F36: Samuel Johnson | G36: Low | H36: 44378 | I36: Jul | J36: Q3 | K36: 2021 | L36: 3.559 | M36: 320.00 | N36: 525.00 | O36: 1,868,475 | P36: 37.37 | Q36: 1,831,106 | R36: 1,017.34 | S36: 1,138,880 | T36: 692.226
A37: Channel Partners | B37: France | C37: Road Racer | D37: CUST_ID_036 | E37: PROD_ID_005 | F37: Harper Anderson | G37: Low | H37: 44541 | I37: Dec | J37: Q4 | K37: 2021 | L37: 1.09 | M37: 4.00 | N37: 18.00 | O37: 19.62 | P37: 589 | Q37: 19.031 | R37: 21094 | S37: 4.36 | T37: 14.671
A38: Government | B38: Germany | C38: X-Terrain | D38: CUST_ID_037 | E38: PROD_ID_001 | F38: Henry Martinez | G38: Low | H38: 43967 | I38: May | J38: Q2 | K38: 2020 | L38: 2.156 | M38: 6.00 | N38: 525.00 | O38: 1,131,900 | P38: 33.957 | Q38: 1,097,943 | R38: 610.08 | S38: 12.936 | T38: 1,085,007
A39: Midmarket | B39: Italy | C39: City Cruiser | D39: CUST_ID_038 | E39: PROD_ID_002 | F39: Amelia Wilson | G39: Low | H39: 44318 | I39: May | J39: Q2 | K39: 2021 | L39: 2.334 | M39: 12.00 | N39: 23.00 | O39: 53.682 | P39: 1.61 | Q39: 52.072 | R39: 28.30 | S39: 28.008 | T39: 24.064
A40: Midmarket | B40: India | C40: Trail Master | D40: CUST_ID_039 | E40: PROD_ID_004 | F40: Jackson Turner | G40: Low | H40: 44288 | I40: Apr | J40: Q2 | K40: 2021 | L40: 2.334 | M40: 308.00 | N40: 23.00 | O40: 53.682 | P40: 1.61 | Q40: 52.072 | R40: 28.30 | S40: 718.872 | T40: -666.8
A41: Government | B41: Japan | C41: City Cruiser | D41: CUST_ID_040 | E41: PROD_ID_002 | F41: Abigail Lewis | G41: Low | H41: 44138 | I41: Nov | J41: Q4 | K41: 2020 | L41: 2.112 | M41: 12.00 | N41: 11.00 | O41: 23.232 | P41: 697 | Q41: 22.535 | R41: 35004 | S41: 25.344 | T41: -2.809
A42: Midmarket | B42: Canada | C42: City Cruiser | D42: CUST_ID_002 | E42: PROD_ID_002 | F42: Emma Johnson | G42: Low | H42: 44296 | I42: Apr | J42: Q2 | K42: 2021 | L42: 2.713 | M42: 12.00 | N42: 23.00 | O42: 62.399 | P42: 2.496 | Q42: 59.903 | R42: 32.56 | S42: 32.556 | T42: 27.347
A43: Government | B43: USA | C43: Speedster | D43: CUST_ID_041 | E43: PROD_ID_003 | F43: Aiden Clark | G43: Low | H43: 44389 | I43: Jul | J43: Q3 | K43: 2021 | L43: 883 | M43: 148.00 | N43: 30.00 | O43: 26.49 | P43: 1.06 | Q43: 25.43 | R43: 14.13 | S43: 130.684 | T43: -105.254
A44: Government | B44: Canada | C44: Road Racer | D44: CUST_ID_042 | E44: PROD_ID_005 | F44: Emily Garcia | G44: Low | H44: 44550 | I44: Dec | J44: Q4 | K44: 2021 | L44: 3.421 | M44: 4.00 | N44: 11.00 | O44: 37.631 | P44: 1.505 | Q44: 36.126 | R44: 19.16 | S44: 13.684 | T44: 22.442
A45: Government | B45: England | C45: X-Terrain | D45: CUST_ID_043 | E45: PROD_ID_001 | F45: Sebastian Phillips | G45: Low | H45: 44026 | I45: Jul | J45: Q3 | K45: 2020 | L45: 3.421 | M45: 6.00 | N45: 11.00 | O45: 37.631 | P45: 1.505 | Q45: 36.126 | R45: 19.16 | S45: 20.526 | T45: 15.6
A46: Midmarket | B46: Canada | C46: City Cruiser | D46: CUST_ID_026 | E46: PROD_ID_002 | F46: Avery Turner | G46: Low | H46: 43845 | I46: Jan | J46: Q1 | K46: 2020 | L46: 805 | M46: 12.00 | N46: 23.00 | O46: 18.515 | P46: 741 | Q46: 17.774 | R46: 24351 | S46: 9.66 | T46: 8.114
A47: Midmarket | B47: France | C47: City Cruiser | D47: CUST_ID_044 | E47: PROD_ID_002 | F47: Elizabeth Martin | G47: Low | H47: 44277 | I47: Mar | J47: Q1 | K47: 2021 | L47: 1.817 | M47: 12.00 | N47: 23.00 | O47: 41.791 | P47: 1.672 | Q47: 40.119 | R47: 21.80 | S47: 21.804 | T47: 18.315
A48: Government | B48: Japan | C48: Speedster | D48: CUST_ID_016 | E48: PROD_ID_003 | F48: Harper Davis | G48: Low | H48: 44352 | I48: Jun | J48: Q2 | K48: 2021 | L48: 3.175 | M48: 148.00 | N48: 30.00 | O48: 95.25 | P48: 3.81 | Q48: 91.44 | R48: 50.80 | S48: 469.9 | T48: -378.46
A49: Government | B49: USA | C49: Trail Master | D49: CUST_ID_033 | E49: PROD_ID_004 | F49: Logan Garcia | G49: Low | H49: 43877 | I49: Feb | J49: Q1 | K49: 2020 | L49: 419 | M49: 308.00 | N49: 525.00 | O49: 219.975 | P49: 8.799 | Q49: 211.176 | R49: 117.26 | S49: 129.052 | T49: 82.124
A50: Midmarket | B50: Germany | C50: Trail Master | D50: CUST_ID_045 | E50: PROD_ID_004 | F50: Alexander Hill | G50: Low | H50: 44089 | I50: Sep | J50: Q3 | K50: 2020 | L50: 1.817 | M50: 308.00 | N50: 23.00 | O50: 41.791 | P50: 1.672 | Q50: 40.119 | R50: 21.80 | S50: 559.636 | T50: -519.517
A51: Midmarket | B51: Italy | C51: Yellow Edition | D51: CUST_ID_046 | E51: PROD_ID_006 | F51: Avery Anderson | G51: Low | H51: 44488 | I51: Oct | J51: Q4 | K51: 2021 | L51: 805 | M51: 320.00 | N51: 23.00 | O51: 18.515 | P51: 741 | Q51: 17.774 | R51: 24351 | S51: 257.6 | T51: -239.826
A52: Government | B52: India | C52: Yellow Edition | D52: CUST_ID_047 | E52: PROD_ID_006 | F52: Michael Wilson | G52: Low | H52: 44196 | I52: Dec | J52: Q4 | K52: 2020 | L52: 2.134 | M52: 320.00 | N52: 525.00 | O52: 1,120,350 | P52: 44.814 | Q52: 1,075,536 | R52: 597.41 | S52: 682.88 | T52: 392.656
A53: Government | B53: Germany | C53: X-Terrain | D53: CUST_ID_037 | E53: PROD_ID_001 | F53: Henry Martinez | G53: Medium | H53: 44425 | I53: Aug | J53: Q3 | K53: 2021 | L53: 1.391 | M53: 6.00 | N53: 11.00 | O53: 15.301 | P53: 765 | Q53: 14.536 | R53: 26115 | S53: 8.346 | T53: 6.19
A54: Government | B54: France | C54: City Cruiser | D54: CUST_ID_004 | E54: PROD_ID_002 | F54: Olivia Brown | G54: Medium | H54: 44467 | I54: Sep | J54: Q3 | K54: 2021 | L54: 2.819 | M54: 12.00 | N54: 11.00 | O54: 31.009 | P54: 1.55 | Q54: 29.459 | R54: 15.62 | S54: 33.828 | T54: -4.369
A55: Government | B55: England | C55: Yellow Edition | D55: CUST_ID_035 | E55: PROD_ID_006 | F55: Samuel Johnson | G55: Medium | H55: 43918 | I55: Mar | J55: Q1 | K55: 2020 | L55: 1.391 | M55: 320.00 | N55: 11.00 | O55: 15.301 | P55: 765 | Q55: 14.536 | R55: 26115 | S55: 445.12 | T55: -430.584
A56: Government | B56: Japan | C56: Road Racer | D56: CUST_ID_048 | E56: PROD_ID_005 | F56: Sofia Turner | G56: Medium | H56: 44340 | I56: May | J56: Q2 | K56: 2021 | L56: 1.219 | M56: 4.00 | N56: 11.00 | O56: 13.409 | P56: 670 | Q56: 12.739 | R56: 27912 | S56: 4.876 | T56: 7.863
A57: Government | B57: USA | C57: X-Terrain | D57: CUST_ID_049 | E57: PROD_ID_001 | F57: Elijah Perez | G57: Medium | H57: 43929 | I57: Apr | J57: Q2 | K57: 2020 | L57: 864 | M57: 6.00 | N57: 525.00 | O57: 453.6 | P57: 22.68 | Q57: 430.92 | R57: 239.40 | S57: 5.184 | T57: 425.736
A58: Small Business | B58: Canada | C58: X-Terrain | D58: CUST_ID_050 | E58: PROD_ID_001 | F58: Mia Hill | G58: Medium | H58: 43850 | I58: Jan | J58: Q1 | K58: 2020 | L58: 1.32 | M58: 6.00 | N58: 450.00 | O58: 594 | P58: 29.7 | Q58: 564.3 | R58: 313.50 | S58: 7.92 | T58: 556.38
A59: Government | B59: France | C59: City Cruiser | D59: CUST_ID_004 | E59: PROD_ID_002 | F59: Olivia Brown | G59: Medium | H59: 43839 | I59: Jan | J59: Q1 | K59: 2020 | L59: 1.474 | M59: 12.00 | N59: 525.00 | O59: 773.85 | P59: 38.693 | Q59: 735.158 | R59: 408.31 | S59: 17.688 | T59: 717.47
A60: Government | B60: France | C60: City Cruiser | D60: CUST_ID_004 | E60: PROD_ID_002 | F60: Olivia Brown | G60: Medium | H60: 44181 | I60: Dec | J60: Q4 | K60: 2020 | L60: 1.667 | M60: 12.00 | N60: 30.00 | O60: 50.01 | P60: 2.501 | Q60: 47.51 | R60: 26.39 | S60: 20.004 | T60: 27.506
A61: Enterprise | B61: England | C61: City Cruiser | D61: CUST_ID_051 | E61: PROD_ID_002 | F61: Logan Phillips | G61: Medium | H61: 44037 | I61: Jul | J61: Q3 | K61: 2020 | L61: 845 | M61: 12.00 | N61: 188.00 | O61: 158.86 | P61: 7.943 | Q61: 150.917 | R61: 83.60 | S61: 10.14 | T61: 140.777
A62: Government | B62: France | C62: City Cruiser | D62: CUST_ID_004 | E62: PROD_ID_002 | F62: Olivia Brown | G62: Medium | H62: 44104 | I62: Sep | J62: Q3 | K62: 2020 | L62: 2.162 | M62: 12.00 | N62: 30.00 | O62: 64.86 | P62: 3.243 | Q62: 61.617 | R62: 34.24 | S62: 25.944 | T62: 35.673
A63: Government | B63: France | C63: City Cruiser | D63: CUST_ID_052 | E63: PROD_ID_002 | F63: Charlotte Martin | G63: Medium | H63: 44034 | I63: Jul | J63: Q3 | K63: 2020 | L63: 2.563 | M63: 12.00 | N63: 11.00 | O63: 28.193 | P63: 1.41 | Q63: 26.783 | R63: 14.20 | S63: 30.756 | T63: -3.973
A64: Midmarket | B64: Italy | C64: City Cruiser | D64: CUST_ID_038 | E64: PROD_ID_002 | F64: Amelia Wilson | G64: Medium | H64: 44271 | I64: Mar | J64: Q1 | K64: 2021 | L64: 2.539 | M64: 12.00 | N64: 23.00 | O64: 58.397 | P64: 2.92 | Q64: 55.477 | R64: 30.15 | S64: 30.468 | T64: 25.009
A65: Enterprise | B65: Germany | C65: Speedster | D65: CUST_ID_053 | E65: PROD_ID_003 | F65: Samuel Hill | G65: Medium | H65: 43946 | I65: Apr | J65: Q2 | K65: 2020 | L65: 845 | M65: 148.00 | N65: 188.00 | O65: 158.86 | P65: 7.943 | Q65: 150.917 | R65: 83.60 | S65: 125.06 | T65: 25.857
A66: Government | B66: Italy | C66: Speedster | D66: CUST_ID_054 | E66: PROD_ID_003 | F66: Harper Wilson | G66: Medium | H66: 44497 | I66: Oct | J66: Q4 | K66: 2021 | L66: 1.24 | M66: 148.00 | N66: 30.00 | O66: 37.2 | P66: 1.86 | Q66: 35.34 | R66: 19.63 | S66: 183.52 | T66: -148.18
A67: Government | B67: India | C67: Trail Master | D67: CUST_ID_055 | E67: PROD_ID_004 | F67: Henry Turner | G67: Medium | H67: 44081 | I67: Sep | J67: Q3 | K67: 2020 | L67: 1.667 | M67: 308.00 | N67: 30.00 | O67: 50.01 | P67: 2.501 | Q67: 47.51 | R67: 26.39 | S67: 513.436 | T67: -465.927
A68: Government | B68: USA | C68: Trail Master | D68: CUST_ID_033 | E68: PROD_ID_004 | F68: Logan Garcia | G68: Medium | H68: 44015 | I68: Jul | J68: Q3 | K68: 2020 | L68: 1.518 | M68: 308.00 | N68: 30.00 | O68: 45.54 | P68: 2.277 | Q68: 43.263 | R68: 45771 | S68: 467.544 | T68: -424.281
A69: Government | B69: Japan | C69: Trail Master | D69: CUST_ID_056 | E69: PROD_ID_004 | F69: Amelia Perez | G69: Medium | H69: 44043 | I69: Jul | J69: Q3 | K69: 2020 | L69: 2.756 | M69: 308.00 | N69: 30.00 | O69: 82.68 | P69: 4.134 | Q69: 78.546 | R69: 43.64 | S69: 848.848 | T69: -770.302
A70: Government | B70: India | C70: Yellow Edition | D70: CUST_ID_047 | E70: PROD_ID_006 | F70: Michael Wilson | G70: Medium | H70: 44207 | I70: Jan | J70: Q1 | K70: 2021 | L70: 1.474 | M70: 320.00 | N70: 525.00 | O70: 773.85 | P70: 38.693 | Q70: 735.158 | R70: 408.31 | S70: 471.68 | T70: 263.478
A71: Channel Partners | B71: France | C71: Road Racer | D71: CUST_ID_036 | E71: PROD_ID_005 | F71: Harper Anderson | G71: Medium | H71: 44197 | I71: Jan | J71: Q1 | K71: 2021 | L71: 2.759 | M71: 4.00 | N71: 18.00 | O71: 49.662 | P71: 2.98 | Q71: 46.682 | R71: 25.93 | S71: 11.036 | T71: 35.646
A72: Government | B72: USA | C72: Road Racer | D72: CUST_ID_057 | E72: PROD_ID_005 | F72: Jackson Hill | G72: Medium | H72: 43936 | I72: Apr | J72: Q2 | K72: 2020 | L72: 316 | M72: 4.00 | N72: 11.00 | O72: 3.476 | P72: 209 | Q72: 3.267 | R72: 26665 | S72: 1.264 | T72: 2.003
A73: Enterprise | B73: Canada | C73: Road Racer | D73: CUST_ID_058 | E73: PROD_ID_005 | F73: Abigail Phillips | G73: Medium | H73: 44424 | I73: Aug | J73: Q3 | K73: 2021 | L73: 1.064 | M73: 4.00 | N73: 188.00 | O73: 200.032 | P73: 12.002 | Q73: 188.03 | R73: 104.22 | S73: 4.256 | T73: 183.774
A74: Government | B74: England | C74: X-Terrain | D74: CUST_ID_059 | E74: PROD_ID_001 | F74: Aiden Martin | G74: Medium | H74: 44464 | I74: Sep | J74: Q3 | K74: 2021 | L74: 1.684 | M74: 6.00 | N74: 11.00 | O74: 18.524 | P74: 1.111 | Q74: 17.413 | R74: 45170 | S74: 10.104 | T74: 7.309
A75: Channel Partners | B75: France | C75: City Cruiser | D75: CUST_ID_060 | E75: PROD_ID_002 | F75: Emily Garcia | G75: Medium | H75: 43946 | I75: Apr | J75: Q2 | K75: 2020 | L75: 2.759 | M75: 12.00 | N75: 18.00 | O75: 49.662 | P75: 2.98 | Q75: 46.682 | R75: 25.93 | S75: 33.108 | T75: 13.574
A76: Government | B76: England | C76: City Cruiser | D76: CUST_ID_027 | E76: PROD_ID_002 | F76: Michael Hill | G76: Medium | H76: 44305 | I76: Apr | J76: Q2 | K76: 2021 | L76: 872 | M76: 12.00 | N76: 525.00 | O76: 457.8 | P76: 27.468 | Q76: 430.332 | R76: 239.18 | S76: 10.464 | T76: 419.868
A77: Small Business | B77: Germany | C77: Speedster | D77: CUST_ID_061 | E77: PROD_ID_003 | F77: Benjamin Martin | G77: Medium | H77: 43976 | I77: May | J77: Q2 | K77: 2020 | L77: 1.465 | M77: 148.00 | N77: 450.00 | O77: 659.25 | P77: 39.555 | Q77: 619.695 | R77: 344.32 | S77: 216.82 | T77: 402.875
A78: Government | B78: Italy | C78: Speedster | D78: CUST_ID_054 | E78: PROD_ID_003 | F78: Harper Wilson | G78: Medium | H78: 44098 | I78: Sep | J78: Q3 | K78: 2020 | L78: 2.491 | M78: 148.00 | N78: 525.00 | O78: 1,307,775 | P78: 78.467 | Q78: 1,229,309 | R78: 683.00 | S78: 368.668 | T78: 860.641
A79: Small Business | B79: Italy | C79: Trail Master | D79: CUST_ID_062 | E79: PROD_ID_004 | F79: Mia Lewis | G79: Medium | H79: 44063 | I79: Aug | J79: Q3 | K79: 2020 | L79: 1.465 | M79: 308.00 | N79: 450.00 | O79: 659.25 | P79: 39.555 | Q79: 619.695 | R79: 344.32 | S79: 451.22 | T79: 168.475
A80: Government | B80: Canada | C80: Trail Master | D80: CUST_ID_034 | E80: PROD_ID_004 | F80: Charlotte Davis | G80: Medium | H80: 44402 | I80: Jul | J80: Q3 | K80: 2021 | L80: 1.348 | M80: 308.00 | N80: 30.00 | O80: 40.44 | P80: 2.426 | Q80: 38.014 | R80: 45982 | S80: 415.184 | T80: -377.17
A81: Small Business | B81: India | C81: Trail Master | D81: CUST_ID_063 | E81: PROD_ID_004 | F81: Logan Clark | G81: Medium | H81: 43895 | I81: Mar | J81: Q1 | K81: 2020 | L81: 2.923 | M81: 308.00 | N81: 450.00 | O81: 1,315,350 | P81: 78.921 | Q81: 1,236,429 | R81: 686.95 | S81: 900.284 | T81: 336.145
A82: Government | B82: Japan | C82: Yellow Edition | D82: CUST_ID_064 | E82: PROD_ID_006 | F82: Charlotte Anderson | G82: Medium | H82: 44248 | I82: Feb | J82: Q1 | K82: 2021 | L82: 872 | M82: 320.00 | N82: 525.00 | O82: 457.8 | P82: 27.468 | Q82: 430.332 | R82: 239.18 | S82: 279.04 | T82: 151.292
A83: Government | B83: USA | C83: Yellow Edition | D83: CUST_ID_065 | E83: PROD_ID_006 | F83: Samuel Wilson | G83: Medium | H83: 44082 | I83: Sep | J83: Q3 | K83: 2020 | L83: 1.684 | M83: 320.00 | N83: 11.00 | O83: 18.524 | P83: 1.111 | Q83: 17.413 | R83: 45170 | S83: 538.88 | T83: -521.467
A84: Government | B84: USA | C84: Yellow Edition | D84: CUST_ID_065 | E84: PROD_ID_006 | F84: Samuel Wilson | G84: Medium | H84: 44429 | I84: Aug | J84: Q3 | K84: 2021 | L84: 2.491 | M84: 320.00 | N84: 525.00 | O84: 1,307,775 | P84: 78.467 | Q84: 1,229,309 | R84: 683.00 | S84: 797.12 | T84: 432.189
A85: Government | B85: England | C85: X-Terrain | D85: CUST_ID_059 | E85: PROD_ID_001 | F85: Aiden Martin | G85: Medium | H85: 44334 | I85: May | J85: Q2 | K85: 2021 | L85: 2.108 | M85: 6.00 | N85: 30.00 | O85: 63.24 | P85: 3.794 | Q85: 59.446 | R85: 33.03 | S85: 12.648 | T85: 46.798
A86: Government | B86: France | C86: City Cruiser | D86: CUST_ID_052 | E86: PROD_ID_002 | F86: Charlotte Martin | G86: Medium | H86: 44437 | I86: Aug | J86: Q3 | K86: 2021 | L86: 2.108 | M86: 12.00 | N86: 30.00 | O86: 63.24 | P86: 3.794 | Q86: 59.446 | R86: 33.03 | S86: 25.296 | T86: 34.15
A87: Government | B87: Canada | C87: Road Racer | D87: CUST_ID_066 | E87: PROD_ID_005 | F87: Harper Turner | G87: Medium | H87: 44309 | I87: Apr | J87: Q2 | K87: 2021 | L87: 2.201 | M87: 4.00 | N87: 30.00 | O87: 66.03 | P87: 4.622 | Q87: 61.408 | R87: 34.11 | S87: 8.804 | T87: 52.604
A88: Government | B88: France | C88: City Cruiser | D88: CUST_ID_052 | E88: PROD_ID_002 | F88: Charlotte Martin | G88: Medium | H88: 44233 | I88: Feb | J88: Q1 | K88: 2021 | L88: 1.237 | M88: 12.00 | N88: 11.00 | O88: 13.607 | P88: 952 | Q88: 12.655 | R88: 26085 | S88: 14.844 | T88: -2.189
A89: Channel Partners | B89: England | C89: Trail Master | D89: CUST_ID_067 | E89: PROD_ID_004 | F89: Henry Phillips | G89: Medium | H89: 43832 | I89: Jan | J89: Q1 | K89: 2020 | L89: 2.658 | M89: 308.00 | N89: 18.00 | O89: 47.844 | P89: 3.349 | Q89: 44.495 | R89: 24.72 | S89: 818.664 | T89: -774.169
A90: Enterprise | B90: France | C90: X-Terrain | D90: CUST_ID_068 | E90: PROD_ID_001 | F90: Amelia Martin | G90: Medium | H90: 43903 | I90: Mar | J90: Q1 | K90: 2020 | L90: 3 | M90: 6.00 | N90: 188.00 | O90: 564 | P90: 39.48 | Q90: 524.52 | R90: 290.63 | S90: 18 | T90: 506.52
A91: Midmarket | B91: Canada | C91: City Cruiser | D91: CUST_ID_026 | E91: PROD_ID_002 | F91: Avery Turner | G91: Medium | H91: 44086 | I91: Sep | J91: Q3 | K91: 2020 | L91: 3.517 | M91: 12.00 | N91: 23.00 | O91: 80.891 | P91: 5.662 | Q91: 75.229 | R91: 40.89 | S91: 42.204 | T91: 33.025
A92: Small Business | B92: Germany | C92: City Cruiser | D92: CUST_ID_069 | E92: PROD_ID_002 | F92: Jackson Hill | G92: Medium | H92: 43998 | I92: Jun | J92: Q2 | K92: 2020 | L92: 1.348 | M92: 12.00 | N92: 450.00 | O92: 606.6 | P92: 42.462 | Q92: 564.138 | R92: 313.32 | S92: 16.176 | T92: 547.962
A93: Small Business | B93: Italy | C93: City Cruiser | D93: CUST_ID_070 | E93: PROD_ID_002 | F93: Abigail Garcia | G93: Medium | H93: 44335 | I93: May | J93: Q2 | K93: 2021 | L93: 1.685 | M93: 12.00 | N93: 450.00 | O93: 758.25 | P93: 53.078 | Q93: 705.173 | R93: 391.72 | S93: 20.22 | T93: 684.953
A94: Channel Partners | B94: India | C94: City Cruiser | D94: CUST_ID_071 | E94: PROD_ID_002 | F94: Aiden Perez | G94: Medium | H94: 43928 | I94: Apr | J94: Q2 | K94: 2020 | L94: 3.316 | M94: 12.00 | N94: 18.00 | O94: 59.688 | P94: 4.178 | Q94: 55.51 | R94: 30.84 | S94: 39.792 | T94: 15.718
A95: Government | B95: Japan | C95: City Cruiser | D95: CUST_ID_072 | E95: PROD_ID_002 | F95: Emily Hill | G95: Medium | H95: 44361 | I95: Jun | J95: Q2 | K95: 2021 | L95: 2.55 | M95: 12.00 | N95: 11.00 | O95: 28.05 | P95: 1.964 | Q95: 26.087 | R95: 13.83 | S95: 30.6 | T95: -4.514
A96: Government | B96: USA | C96: Speedster | D96: CUST_ID_041 | E96: PROD_ID_003 | F96: Aiden Clark | G96: Medium | H96: 44238 | I96: Feb | J96: Q1 | K96: 2021 | L96: 1.705 | M96: 148.00 | N96: 30.00 | O96: 51.15 | P96: 3.581 | Q96: 47.57 | R96: 26.43 | S96: 252.34 | T96: -204.771
A97: Government | B97: France | C97: Speedster | D97: CUST_ID_028 | E97: PROD_ID_003 | F97: Sofia Phillips | G97: Medium | H97: 44321 | I97: May | J97: Q2 | K97: 2021 | L97: 706 | M97: 148.00 | N97: 30.00 | O97: 21.18 | P97: 1.483 | Q97: 19.697 | R97: 34608 | S97: 104.488 | T97: -84.791
A98: Enterprise | B98: USA | C98: Yellow Edition | D98: CUST_ID_073 | E98: PROD_ID_006 | F98: Benjamin Phillips | G98: Medium | H98: 44353 | I98: Jun | J98: Q2 | K98: 2021 | L98: 1.193 | M98: 320.00 | N98: 188.00 | O98: 224.284 | P98: 15.7 | Q98: 208.584 | R98: 115.55 | S98: 381.76 | T98: -173.176
A99: Small Business | B99: Canada | C99: X-Terrain | D99: CUST_ID_074 | E99: PROD_ID_001 | F99: Mia Turner | G99: Medium | H99: 44056 | I99: Aug | J99: Q3 | K99: 2020 | L99: 1.54 | M99: 6.00 | N99: 450.00 | O99: 693 | P99: 55.44 | Q99: 637.56 | R99: 354.11 | S99: 9.24 | T99: 628.32
A100: Government | B100: Japan | C100: City Cruiser | D100: CUST_ID_072 | E100: PROD_ID_002 | F100: Emily Hill | G100: Medium | H100: 44514 | I100: Nov | J100: Q4 | K100: 2021 | L100: 2.891 | M100: 12.00 | N100: 11.00 | O100: 31.801 | P100: 2.544 | Q100: 29.257 | R100: 15.51 | S100: 34.692 | T100: -5.435
...

Sheet Analysis
A2: Segment
A3: Row Labels | B3: Sum of Net Sales | D3: Row Labels | E3: Sum of Net Sales | G3: Product name | J3: Month | V3: Row Labels | W3: Sum of Net Sales
A4: Channel Partners | B4: 3241.054 | D4: Canada | E4: 13485.657 | J4: Row Labels | K4: Sum of Net Sales | L4: Month | M4: Actual | N4: Budget | O4: Actual | P4: Budget | S4: Row Labels | T4: Sum of Net Sales | V4: Abigail Clark | W4: 42.412
A5: Enterprise | B5: 35394.76 | D5: England | E5: 14649.515 | J5: Jan | K5: 12734.705 | L5: =J5 -> Jan | M5: =GETPIVOTDATA("Net Sales",$K$5,"Month",L5) -> 12734.705 | N5: =Sheet4!A2 -> £18,300,908 | S5: 2020 | T5: 59230.128 | V5: Abigail Garcia | W5: 3173.568
A6: Government | B6: 42685.77 | D6: France | E6: 10781.288 | J6: Feb | K6: 11408.102 | L6: =J6 -> Feb | M6: =GETPIVOTDATA("Net Sales",$K$5,"Month",L6) -> 11408.102 | N6: =Sheet4!A3 -> £23,544,303 | S6: 2021 | T6: 58713.748 | V6: Abigail Lewis | W6: 2362.966
A7: Midmarket | B7: 4382.609 | D7: Germany | E7: 18164.176 | J7: Mar | K7: 5961.393 | L7: =J7 -> Mar | M7: =GETPIVOTDATA("Net Sales",$K$5,"Month",L7) -> 5961.393 | N7: =Sheet4!A4 -> £21,303,974 | S7: Grand Total | T7: 117943.88 | V7: Abigail Martin | W7: 1314.275
A8: Small Business | B8: 32239.683 | D8: India | E8: 15520.059 | J8: Apr | K8: 10336.968 | L8: =J8 -> Apr | M8: =GETPIVOTDATA("Net Sales",$K$5,"Month",L8) -> 10336.968 | N8: =Sheet4!A5 -> £10,611,142 | V8: Abigail Phillips | W8: 1448.544
A9: Grand Total | B9: 117943.88 | D9: Italy | E9: 15582.742 | J9: May | K9: 10306.451 | L9: =J9 -> May | M9: =GETPIVOTDATA("Net Sales",$K$5,"Month",L9) -> 10306.451 | N9: =Sheet4!A6 -> £14,661,451 | V9: Abigail Robinson | W9: 474.323
B10: =GETPIVOTDATA("Net Sales",$A$3) -> 117943.88 | D10: Japan | E10: 16333.316 | J10: Jun | K10: 10935.368 | L10: =J10 -> Jun | M10: =GETPIVOTDATA("Net Sales",$K$5,"Month",L10) -> 10935.368 | N10: =Sheet4!A7 -> £22,614,104 | V10: Aiden Anderson | W10: 77.87
D11: USA | E11: 13427.123 | J11: Jul | K11: 11102.754 | L11: =J11 -> Jul | M11: =GETPIVOTDATA("Net Sales",$K$5,"Month",L11) -> 11102.754 | N11: =Sheet4!A8 -> £18,334,867 | V11: Aiden Clark | W11: 1192.497
D12: Grand Total | E12: 117943.88 | J12: Aug | K12: 8161.552 | L12: =J12 -> Aug | M12: =GETPIVOTDATA("Net Sales",$K$5,"Month",L12) -> 8161.552 | N12: =Sheet4!A9 -> £20,514,113 | V12: Aiden Garcia | W12: 871.167
J13: Sep | K13: 6882.857 | L13: =J13 -> Sep | M13: =GETPIVOTDATA("Net Sales",$K$5,"Month",L13) -> 6882.857 | N13: =Sheet4!A10 -> £20,199,830 | V13: Aiden Hill | W13: 167.14
J14: Oct | K14: 10989.934 | L14: =J14 -> Oct | M14: =GETPIVOTDATA("Net Sales",$K$5,"Month",L14) -> 10989.934 | N14: =Sheet4!A11 -> £12,194,030 | V14: Aiden Lewis | W14: 1173.382
J15: Nov | K15: 8667.366 | L15: =J15 -> Nov | M15: =GETPIVOTDATA("Net Sales",$K$5,"Month",L15) -> 8667.366 | N15: =Sheet4!A12 -> £12,337,191 | V15: Aiden Martin | W15: 2054.159
J16: Dec | K16: 10456.426 | L16: =J16 -> Dec | M16: =GETPIVOTDATA("Net Sales",$K$5,"Month",L16) -> 10456.426 | N16: =Sheet4!A13 -> £15,522,499 | O16: =M16 -> 10456.426 | P16: =N16 -> £15,522,499 | V16: Aiden Perez | W16: 96.394
J17: Grand Total | K17: 117943.88 | N17: =Sheet4!A14 -> £210,138,410 | V17: Alexander Hill | W17: 56.037
V18: Alexander Perez | W18: 195.497
V19: Amelia Garcia | W19: 222.535
V20: Amelia Hill | W20: 509.904
A21: PROFIT | V21: Amelia Martin | W21: 2025.813
V22: Amelia Perez | W22: 410.782
A23: Row Labels | B23: Sum of Profit | D23: Row Labels | E23: Sum of Profit | I23: Row Labels | J23: Sum of Net Sales | V23: Amelia Phillips | W23: 972.834
A24: Channel Partners | B24: -17220.726 | D24: Canada | E24: 1703.041 | F24: =GETPIVOTDATA("Profit",$D$23,"Country",D24) -> 1703.041 | G24: =SUM(F24)/SUM($F$24:$F$31) -> 0.08169547 | I24: City Cruiser | J24: 32667.544 | K24: =GETPIVOTDATA("Net Sales",$I$23,"Product_Name",I24) -> 32667.544 | L24: =SUM(K24)/SUM($K$24:$K$29) -> 0.27697533 | V24: Amelia Wilson | W24: 207.353
A25: Enterprise | B25: 12877.01 | D25: England | E25: 2621.577 | F25: =GETPIVOTDATA("Profit",$D$23,"Country",D25) -> 2621.577 | G25: =SUM(F25)/SUM($F$24:$F$31) -> 0.12575796 | I25: X-Terrain | J25: 17550.051 | K25: =GETPIVOTDATA("Net Sales",$I$23,"Product_Name",I25) -> 17550.051 | L25: =SUM(K25)/SUM($K$24:$K$29) -> 0.14880002 | V25: Ava Davis | W25: 364.587
A26: Government | B26: 5933.185 | D26: France | E26: 2983.784 | F26: =GETPIVOTDATA("Profit",$D$23,"Country",D26) -> 2983.784 | G26: =SUM(F26)/SUM($F$24:$F$31) -> 0.14313316 | I26: Road Racer | J26: 17276.45 | K26: =GETPIVOTDATA("Net Sales",$I$23,"Product_Name",I26) -> 17276.45 | L26: =SUM(K26)/SUM($K$24:$K$29) -> 0.14648026 | V26: Avery Anderson | W26: 175.226
A27: Midmarket | B27: -13869.991 | D27: Germany | E27: 7633.574 | F27: =GETPIVOTDATA("Profit",$D$23,"Country",D27) -> 7633.574 | G27: =SUM(F27)/SUM($F$24:$F$31) -> 0.3661852 | I27: Speedster | J27: 17588.964 | K27: =GETPIVOTDATA("Net Sales",$I$23,"Product_Name",I27) -> 17588.964 | L27: =SUM(K27)/SUM($K$24:$K$29) -> 0.14912995 | V27: Avery Turner | W27: 407.634
A28: Small Business | B28: 33126.733 | D28: India | E28: -3228.023 | F28: =GETPIVOTDATA("Profit",$D$23,"Country",D28) -> -3228.023 | G28: =SUM(F28)/SUM($F$24:$F$31) -> -0.15484939 | I28: Trail Master | J28: 18000.232 | K28: =GETPIVOTDATA("Net Sales",$I$23,"Product_Name",I28) -> 18000.232 | L28: =SUM(K28)/SUM($K$24:$K$29) -> 0.15261693 | V28: Benjamin Garcia | W28: 2248.431
A29: Grand Total | B29: 20846.211 | D29: Italy | E29: 10867.723 | F29: =GETPIVOTDATA("Profit",$D$23,"Country",D29) -> 10867.723 | G29: =SUM(F29)/SUM($F$24:$F$31) -> 0.52132846 | I29: Yellow Edition | J29: 14860.635 | K29: =GETPIVOTDATA("Net Sales",$I$23,"Product_Name",I29) -> 14860.635 | L29: =SUM(K29)/SUM($K$24:$K$29) -> 0.12599751 | V29: Benjamin Hill | W29: 315.468
D30: Japan | E30: 3746.768 | F30: =GETPIVOTDATA("Profit",$D$23,"Country",D30) -> 3746.768 | G30: =SUM(F30)/SUM($F$24:$F$31) -> 0.17973377 | I30: Grand Total | J30: 117943.88 | V30: Benjamin Lee | W30: 1094.198
D31: USA | E31: -5482.233 | F31: =GETPIVOTDATA("Profit",$D$23,"Country",D31) -> -5482.233 | G31: =SUM(F31)/SUM($F$24:$F$31) -> -0.26298463 | V31: Benjamin Martin | W31: 2059.331
D32: Grand Total | E32: 20846.211 | F32: =GETPIVOTDATA("Profit",$D$23) -> 20846.211 | V32: Benjamin Martinez | W32: 636.089
V33: Benjamin Phillips | W33: 3775.86
V34: Charlotte Anderson | W34: 716.46
V35: Charlotte Davis | W35: 1039.715
V36: Charlotte Garcia | W36: 2073.587
A37: UNIT SOLD | V37: Charlotte Hill | W37: 468.174
V38: Charlotte Martin | W38: 2182.142
A39: Row Labels | B39: Sum of Units Sold | D39: Row Labels | E39: Sum of Units Sold | V39: Charlotte White | W39: 78.229
A40: Channel Partners | B40: 12575.121 | D40: Canada | E40: 9657.981 | V40: Elijah Martin | W40: 789.581
A41: Enterprise | B41: 18571.872 | D41: England | E41: 15507.397 | V41: Elijah Perez | W41: 1199.299
A42: Government | B42: 38912.416 | D42: France | E42: 9371.344 | V42: Elizabeth Green | W42: 1933.529
A43: Midmarket | B43: 16109.692 | D43: Germany | E43: 17245.5 | V43: Elizabeth Martin | W43: 247.001
A44: Small Business | B44: 14712.225 | D44: India | E44: 14352.347 | V44: Emily Clark | W44: 613.542
A45: Grand Total | B45: 100881.33 | D45: Italy | E45: 8595.727 | V45: Emily Garcia | W45: 936.353
D46: Japan | E46: 13779.037 | V46: Emily Hill | W46: 3101.545
A47: =GETPIVOTDATA("Units Sold",$A$39) -> 100881.33 | D47: USA | E47: 12371.993 | V47: Emily Martin | W47: 276.537
D48: Grand Total | E48: 100881.33 | V48: Emily Phillips | W48: 85.122
V49: Emma Johnson | W49: 443.649
V50: Ethan Miller | W50: 1430.862
V51: Harper Anderson | W51: 199.105
A52: Revenue | B52: =GETPIVOTDATA("Net Sales",$A$3) -> 117943.88 | V52: Harper Davis | W52: 1035.452
A53: Profit | B53: =GETPIVOTDATA("Profit",$A$23) -> 20846.211 | V53: Harper Hill | W53: 2340.099
B54: =B53/B52 -> 0.17674687 | V54: Harper Martin | W54: 1049.439
V55: Harper Phillips | W55: 1581.933
V56: Harper Turner | W56: 3085.409
V57: Harper Wilson | W57: 1653.35
V58: Henry Anderson | W58: 473.972
V59: Henry Garcia | W59: 1816.928
V60: Henry Martin | W60: 1230.907
V61: Henry Martinez | W61: 2128.875
V62: Henry Phillips | W62: 175.044
V63: Henry Turner | W63: 1866.848
V64: Isabella Wilson | W64: 2354.602
V65: Jackson Hill | W65: 6261.973
V66: Jackson Lewis | W66: 130.127
... V98: Grand Total | W98: 117943.88

Sheet Sheet4
A1: Budget
A2: £18,300,908
A3: £23,544,303
A4: £21,303,974
A5: £10,611,142
A6: £14,661,451
A7: £22,614,104
A8: £18,334,867
A9: £20,514,113
A10: £20,199,830
A11: £12,194,030
A12: £12,337,191
... A19: Target
A20: Revenue | B20: £210,138,410
A21: Profit | B21: £60,429,310
A22: Profit Margin | B22: 28.76%
A23: Unit Sold | B23: 1,420,956

Sheet DASHBOARD
